nldata/__init__.py
nldata/corpora/__init__.py
nldata/corpora/bnc.py
nldata/corpora/corpus.py
nldata/corpora/ptb.py
nldata/corpora/ptnews.py
nldata/corpora/telegram.py
nldata/corpora/text8.py
nldata/corpora/wacky.py
nldata/corpora/wiki103.py
nldata/iterx.py
nldata/nlp/__init__.py
nldata/nlp/patterns.py
nldata/nlp/ptstop.py
nldata/nlp/regex_utils.py
nldata/nlp/token.py
nldata/utils.py
nldata-0.5.0.dist-info/WHEEL
nldata-0.5.0.dist-info/METADATA
nldata-0.5.0.dist-info/RECORD
